{
  "source": "autonomy",
  "collected_at": "2026-03-13T20:30:13Z",
  "date": "2026-03-13",
  "autonomy_score": 55,
  "totals": {
    "heal_events_today": 0,
    "service_restarts_today": 606,
    "failed_units": 10,
    "active_timers": 35,
    "total_cron_jobs": 95,
    "max_uptime_days": 2
  },
  "nodes": {
    "alice": {
      "heal_events_today": 0,
      "service_restarts_today": 168,
      "failed_units": 3,
      "cron_jobs": 9,
      "user_cron_jobs": 12,
      "active_timers": 11,
      "power_monitor_entries": 187,
      "docker_auto_restarts": 0,
      "uptime_days": 2
    },
    "cecilia": {
      "heal_events_today": 0,
      "service_restarts_today": 0,
      "failed_units": 4,
      "cron_jobs": 16,
      "user_cron_jobs": 18,
      "active_timers": 11,
      "power_monitor_entries": 198,
      "docker_auto_restarts": 0,
      "uptime_days": 0
    },
    "octavia": {
      "status": "unreachable"
    },
    "lucidia": {
      "heal_events_today": 0,
      "service_restarts_today": 438,
      "failed_units": 3,
      "cron_jobs": 15,
      "user_cron_jobs": 25,
      "active_timers": 13,
      "power_monitor_entries": 200,
      "docker_auto_restarts": 0,
      "uptime_days": 0
    }
  }
}